[{"image_id":"118014929","ext":"gif","sha256":"3b92b8f7b5b78ff3652790b7dc165a705b16e15f05bc77165dcf0abf7a5309dd","converted_text":"","status":"downloaded","refs":[{"doc_path":"legalize-kr/kr/국민체육진흥법/시행령.md","line_number":1423,"law_name":"국민체육진흥법","file_name":"시행령","github_url":"https://github.com/legalize-kr/legalize-kr/blob/main/kr/국민체육진흥법/시행령.md#L1423","law_url":"https://www.law.go.kr/법령/국민체육진흥법"}]},{"image_id":"12865829","ext":"gif","sha256":"fef23515a066fda329f7d1c2042008f7e0311b1bfb8af56d5230a50396666cdf","converted_text":"","status":"downloaded","refs":[{"doc_path":"legalize-kr/kr/건설기계안전기준에관한규칙/국토교통부령.md","line_number":190,"law_name":"건설기계안전기준에관한규칙","file_name":"국토교통부령","github_url":"https://github.com/legalize-kr/legalize-kr/blob/main/kr/건설기계안전기준에관한규칙/국토교통부령.md#L190","law_url":"https://www.law.go.kr/법령/건설기계안전기준에관한규칙"},{"doc_path":"legalize-kr/kr/건설기계안전기준에관한규칙/국토해양부령.md","line_number":170,"law_name":"건설기계안전기준에관한규칙","file_name":"국토해양부령","github_url":"https://github.com/legalize-kr/legalize-kr/blob/main/kr/건설기계안전기준에관한규칙/국토해양부령.md#L170","law_url":"https://www.law.go.kr/법령/건설기계안전기준에관한규칙"}]},{"image_id":"13536029","ext":"gif","sha256":"9edccb1e6854fd289c819a3138aaef2da38c236845d8d69be5efce09f1cbabb9","converted_text":"","status":"downloaded","refs":[{"doc_path":"legalize-kr/kr/산업교육진흥및산학연협력촉진에관한법률/시행규칙(교육부령).md","line_number":164,"law_name":"산업교육진흥및산학연협력촉진에관한법률","file_name":"시행규칙(교육부령)","github_url":"https://github.com/legalize-kr/legalize-kr/blob/main/kr/산업교육진흥및산학연협력촉진에관한법률/시행규칙(교육부령).md#L164","law_url":"https://www.law.go.kr/법령/산업교육진흥및산학연협력촉진에관한법률"}]},{"image_id":"156623129","ext":"gif","sha256":"681b4f68347665852a6742331a0fe8dc6d46f4065ddfe3f5e1c74adbb9aa0afc","converted_text":"","status":"downloaded","refs":[{"doc_path":"legalize-kr/kr/정부조직법/법률.md","line_number":16526,"law_name":"정부조직법","file_name":"법률","github_url":"https://github.com/legalize-kr/legalize-kr/blob/main/kr/정부조직법/법률.md#L16526","law_url":"https://www.law.go.kr/법령/정부조직법"}]},{"image_id":"15995129","ext":"gif","sha256":"d010f40a9055aa35cfbd884f70277508835ef9bb75d373b42da2f752a68ab691","converted_text":"","status":"downloaded","refs":[{"doc_path":"legalize-kr/kr/사법정책연구원운영규칙/대법원규칙.md","line_number":234,"law_name":"사법정책연구원운영규칙","file_name":"대법원규칙","github_url":"https://github.com/legalize-kr/legalize-kr/blob/main/kr/사법정책연구원운영규칙/대법원규칙.md#L234","law_url":"https://www.law.go.kr/법령/사법정책연구원운영규칙"}]},{"image_id":"19410029","ext":"gif","sha256":"cd725fb45ac2871f66271c371bcbf7ad9295808e402a6680de244fd7b3dea803","converted_text":"","status":"downloaded","refs":[{"doc_path":"legalize-kr/kr/국가기술자격법/시행규칙(고용노동부령).md","line_number":5809,"law_name":"국가기술자격법","file_name":"시행규칙(고용노동부령)","github_url":"https://github.com/legalize-kr/legalize-kr/blob/main/kr/국가기술자격법/시행규칙(고용노동부령).md#L5809","law_url":"https://www.law.go.kr/법령/국가기술자격법"}]},{"image_id":"27657929","ext":"gif","sha256":"bda2c8b2738c743d6c87bd94b70dc7d4da4c778cd263aa6f641409e6d386362b","converted_text":"","status":"downloaded","refs":[{"doc_path":"legalize-kr/kr/교원자격검정령/시행규칙(교육부령).md","line_number":853,"law_name":"교원자격검정령","file_name":"시행규칙(교육부령)","github_url":"https://github.com/legalize-kr/legalize-kr/blob/main/kr/교원자격검정령/시행규칙(교육부령).md#L853","law_url":"https://www.law.go.kr/법령/교원자격검정령"}]},{"image_id":"34721129","ext":"gif","sha256":"b227d52a35a416e8ff1446776ebbca8263957a7c6dac19d87c3b90c44505bf4b","converted_text":"","status":"downloaded","refs":[{"doc_path":"legalize-kr/kr/건설기계안전기준에관한규칙/국토교통부령.md","line_number":1250,"law_name":"건설기계안전기준에관한규칙","file_name":"국토교통부령","github_url":"https://github.com/legalize-kr/legalize-kr/blob/main/kr/건설기계안전기준에관한규칙/국토교통부령.md#L1250","law_url":"https://www.law.go.kr/법령/건설기계안전기준에관한규칙"}]},{"image_id":"66400529","ext":"gif","sha256":"e6db2235388cab054391ad7cc657a15be9789a80d43ee593329950629974fd46","converted_text":"","status":"downloaded","refs":[{"doc_path":"legalize-kr/kr/군인연금법/시행령.md","line_number":718,"law_name":"군인연금법","file_name":"시행령","github_url":"https://github.com/legalize-kr/legalize-kr/blob/main/kr/군인연금법/시행령.md#L718","law_url":"https://www.law.go.kr/법령/군인연금법"}]},{"image_id":"6928229","ext":"gif","sha256":"a162687547995e72dd0e7c0f09d1c4c3bcf61b983102ec4e8366814ca6144a1d","converted_text":"","status":"downloaded","refs":[{"doc_path":"legalize-kr/kr/119구조ㆍ구급에관한법률/시행규칙(총리령).md","line_number":357,"law_name":"119구조ㆍ구급에관한법률","file_name":"시행규칙(총리령)","github_url":"https://github.com/legalize-kr/legalize-kr/blob/main/kr/119구조ㆍ구급에관한법률/시행규칙(총리령).md#L357","law_url":"https://www.law.go.kr/법령/119구조ㆍ구급에관한법률"},{"doc_path":"legalize-kr/kr/119구조ㆍ구급에관한법률/시행규칙(행정안전부령).md","line_number":429,"law_name":"119구조ㆍ구급에관한법률","file_name":"시행규칙(행정안전부령)","github_url":"https://github.com/legalize-kr/legalize-kr/blob/main/kr/119구조ㆍ구급에관한법률/시행규칙(행정안전부령).md#L429","law_url":"https://www.law.go.kr/법령/119구조ㆍ구급에관한법률"},{"doc_path":"legalize-kr/kr/119구조ㆍ구급에관한법률/시행규칙.md","line_number":315,"law_name":"119구조ㆍ구급에관한법률","file_name":"시행규칙","github_url":"https://github.com/legalize-kr/legalize-kr/blob/main/kr/119구조ㆍ구급에관한법률/시행규칙.md#L315","law_url":"https://www.law.go.kr/법령/119구조ㆍ구급에관한법률"}]},{"image_id":"80302529","ext":"gif","sha256":"d12374be0cd91bcfcc7d216e493ee5d8bac8ec2084472393b5ca9e95bc6239cc","converted_text":"","status":"downloaded","refs":[{"doc_path":"legalize-kr/kr/공인중개사법/시행규칙.md","line_number":609,"law_name":"공인중개사법","file_name":"시행규칙","github_url":"https://github.com/legalize-kr/legalize-kr/blob/main/kr/공인중개사법/시행규칙.md#L609","law_url":"https://www.law.go.kr/법령/공인중개사법"},{"doc_path":"legalize-kr/kr/부동산거래신고등에관한법률/시행규칙.md","line_number":537,"law_name":"부동산거래신고등에관한법률","file_name":"시행규칙","github_url":"https://github.com/legalize-kr/legalize-kr/blob/main/kr/부동산거래신고등에관한법률/시행규칙.md#L537","law_url":"https://www.law.go.kr/법령/부동산거래신고등에관한법률"}]}]